osprey/__init__.py
osprey/approval/__init__.py
osprey/approval/approval_manager.py
osprey/approval/approval_system.py
osprey/approval/config_models.py
osprey/approval/evaluators.py
osprey/assist/README.md
osprey/assist/integrations/claude_code/migrate/SKILL.md
osprey/assist/integrations/claude_code/pre-commit/SKILL.md
osprey/assist/integrations/claude_code/release-workflow/SKILL.md
osprey/assist/tasks/ai-code-review/instructions.md
osprey/assist/tasks/channel-finder-database-builder/instructions.md
osprey/assist/tasks/channel-finder-pipeline-selection/instructions.md
osprey/assist/tasks/comments/instructions.md
osprey/assist/tasks/commit-organization/instructions.md
osprey/assist/tasks/create-capability/instructions.md
osprey/assist/tasks/docstrings/instructions.md
osprey/assist/tasks/migrate/instructions.md
osprey/assist/tasks/migrate/schema.yml
osprey/assist/tasks/migrate/authoring/README.md
osprey/assist/tasks/migrate/authoring/migration-workflow.md
osprey/assist/tasks/migrate/authoring/examples/v0.9.6.yml
osprey/assist/tasks/migrate/authoring/prompts/audit.md
osprey/assist/tasks/migrate/authoring/prompts/generate.md
osprey/assist/tasks/migrate/authoring/prompts/validate.md
osprey/assist/tasks/migrate/authoring/tools/__init__.py
osprey/assist/tasks/migrate/authoring/tools/migrate.py
osprey/assist/tasks/migrate/versions/v0.9.6.yml
osprey/assist/tasks/migrate-project/instructions.md
osprey/assist/tasks/pre-commit/instructions.md
osprey/assist/tasks/pre-merge-cleanup/instructions.md
osprey/assist/tasks/release-workflow/instructions.md
osprey/assist/tasks/testing-workflow/instructions.md
osprey/assist/tasks/update-documentation/instructions.md
osprey/base/__init__.py
osprey/base/capability.py
osprey/base/decorators.py
osprey/base/errors.py
osprey/base/examples.py
osprey/base/nodes.py
osprey/base/planning.py
osprey/base/results.py
osprey/capabilities/context_tools.py
osprey/capabilities/memory.py
osprey/capabilities/python.py
osprey/capabilities/state_manager_chat.py
osprey_framework-0.10.7.dist-info/licenses/LICENSE.txt
osprey_framework-0.10.7.dist-info/METADATA
osprey_framework-0.10.7.dist-info/WHEEL
osprey_framework-0.10.7.dist-info/entry_points.txt
osprey_framework-0.10.7.dist-info/top_level.txt
osprey_framework-0.10.7.dist-info/RECORD
