Metadata-Version: 2.4
Name: osprey-framework
Version: 0.10.7
Summary: An open-source, domain-agnostic, capability-based architecture for building intelligent agents
Author-email: Thorsten Hellert <thellert@lbl.gov>
Maintainer-email: Thorsten Hellert <thellert@lbl.gov>
License: BSD-3-Clause
Project-URL: Homepage, https://als-apg.github.io/osprey
Project-URL: Documentation, https://als-apg.github.io/osprey
Project-URL: Repository, https://github.com/als-apg/osprey
Project-URL: Paper, https://arxiv.org/abs/2508.15066
Project-URL: Issues, https://github.com/als-apg/osprey/issues
Project-URL: Changelog, https://github.com/als-apg/osprey/blob/main/CHANGELOG.md
Keywords: ai,agents,framework,scientific-computing,langgraph,epics,accelerator-physics,als,berkeley,agent-framework,capability-based,human-in-the-loop,container-orchestration
Classifier: Development Status :: 3 - Alpha
Classifier: Intended Audience :: Developers
Classifier: Intended Audience :: Science/Research
Classifier: License :: OSI Approved :: BSD License
Classifier: Operating System :: OS Independent
Classifier: Programming Language :: Python :: 3
Classifier: Programming Language :: Python :: 3.11
Classifier: Programming Language :: Python :: 3.12
Classifier: Topic :: Scientific/Engineering
Classifier: Topic :: Scientific/Engineering :: Physics
Classifier: Topic :: Software Development :: Libraries :: Python Modules
Classifier: Topic :: System :: Distributed Computing
Requires-Python: >=3.11
License-File: LICENSE.txt
Requires-Dist: langgraph>=0.5.2
Requires-Dist: langchain-core>=0.3.68
Requires-Dist: langgraph-sdk<0.4.0,>=0.1.70
Requires-Dist: rich>=14.0.0
Requires-Dist: click>=8.1.0
Requires-Dist: questionary>=2.0.0
Requires-Dist: python-dotenv>=1.1.0
Requires-Dist: PyYAML>=6.0.2
Requires-Dist: Jinja2>=3.1.6
Requires-Dist: requests>=2.32.3
Requires-Dist: nbformat>=5.0.0
Requires-Dist: nbclient
Requires-Dist: litellm>=1.56.0
Requires-Dist: openai>=2
Requires-Dist: anthropic
Requires-Dist: google-generativeai
Requires-Dist: ollama>=0.5.1
Requires-Dist: claude-agent-sdk>=0.1.26
Requires-Dist: pandas>=2.2.3
Requires-Dist: numpy>=2.2.6
Requires-Dist: matplotlib>=3.10.3
Requires-Dist: aiohttp>=3.10
Requires-Dist: websocket-client>=1.7.0
Requires-Dist: urllib3>=2.4.0
Requires-Dist: certifi>=2025.4.26
Requires-Dist: charset-normalizer>=3.4.2
Requires-Dist: idna>=3.10
Requires-Dist: MarkupSafe>=3.0.2
Requires-Dist: textual>=0.70.0
Requires-Dist: langchain-openai>=0.3.0
Requires-Dist: fastmcp>=2.0.0
Requires-Dist: langchain-mcp-adapters
Requires-Dist: scipy>=1.15.3
Requires-Dist: seaborn
Requires-Dist: scikit-learn
Requires-Dist: ipywidgets
Requires-Dist: nltk>=3.8.1
Requires-Dist: unique-namer>=0.1.0
Requires-Dist: caproto
Provides-Extra: docs
Requires-Dist: sphinx>=8.0.0; extra == "docs"
Requires-Dist: pydata-sphinx-theme; extra == "docs"
Requires-Dist: myst-parser; extra == "docs"
Requires-Dist: sphinx-copybutton; extra == "docs"
Requires-Dist: sphinx-autobuild; extra == "docs"
Requires-Dist: sphinx-design; extra == "docs"
Requires-Dist: sphinxcontrib-mermaid; extra == "docs"
Requires-Dist: sphinxcontrib-jsmath>=1.0.1; extra == "docs"
Requires-Dist: graphviz; extra == "docs"
Provides-Extra: dev
Requires-Dist: pytest; extra == "dev"
Requires-Dist: pytest-asyncio; extra == "dev"
Requires-Dist: pytest-cov; extra == "dev"
Requires-Dist: pytest-vcr; extra == "dev"
Requires-Dist: vcrpy; extra == "dev"
Requires-Dist: mypy; extra == "dev"
Requires-Dist: pre-commit; extra == "dev"
Requires-Dist: ruff; extra == "dev"
Requires-Dist: pyepics; extra == "dev"
Requires-Dist: build; extra == "dev"
Provides-Extra: storage
Requires-Dist: pymongo; extra == "storage"
Requires-Dist: neo4j; extra == "storage"
Requires-Dist: qdrant-client; extra == "storage"
Requires-Dist: langgraph-checkpoint-postgres<4.0.0,>=2.0.22; extra == "storage"
Requires-Dist: psycopg[pool]<4.0.0,>=3.1.0; extra == "storage"
Requires-Dist: psycopg-pool<4.0.0,>=3.1.0; extra == "storage"
Requires-Dist: langchain-postgres<0.1.0,>=0.0.12; extra == "storage"
Requires-Dist: mem0ai>=0.1.88; extra == "storage"
Requires-Dist: vecs>=0.4.5; extra == "storage"
Provides-Extra: all
Requires-Dist: osprey-framework[dev,docs,storage]; extra == "all"
Dynamic: license-file
